Workbook

Sheet Read Me
A1: Hasiru Agro: New E-Commerce Website, Data Collection Sheet
A2: Prepared by WODO for the Hasiru Agro team. Please fill the yellow cells in every tab.
A4: Purpose | B4: The new website needs product, recommendation, calculator and delivery data to power the features in the SRS. This workbook lists every feature, the data it needs, and gives a place to fill it.
A5: Colour key
B6: Green cells: already taken from the old hasiruagro.com shop. Please check and correct.
B7: Yellow cells: please fill. These are new and required for the new features.
B8: Blue cells: calculated automatically. Do not edit.
A9: Tabs
A10: 1. Feature Map | B10: Every website feature, the SRS section it comes from, and which tab/columns feed it.
A11: 2. Plants | B11: All 193 plants from the old shop, pre-filled. Add new columns (category, weight, spacing, model role, etc.). Add new plants at the bottom.
A12: 3. Input Products | B12: Compost, vermicompost, biochar, seeds, liquid fertiliser, bio-pesticide. New, please fill fully.
A13: 4. Recommendation Models | B13: Commercial, Food Forest, Miyawaki: which plants, their role (main/host/biomass), spacing and quantities.
A14: 5. Calculators | B14: Formulas for the plant, compost, biochar, vermicompost and seed calculators.
A15: 6. Logistics | B15: Vehicles, capacity, delivery zones, Bengaluru schedule, outstation rates, packing charges.
A16: 7. Content & Policies | B16: Checklist of text, logos, photos, videos, testimonials, client and project data.
A17: 8. Category Map | B17: Proposed mapping of old shop categories to the new Timber / Fruiting / Other structure.
A18: Notes
A19: Pricing | B19: Each plant has a normal price (below its bulk quantity) and a bulk price. The bulk quantity differs per plant: e.g. 50 for big trees like mango, 200 for small shrubs. Fill both columns in the Plants tab. Old Regular / Sale / Offline prices are shown for reference.
A20: Sizes | B20: Plant sizes: do any plants come in more than one size (e.g. 1.5 ft and 6 ft)? If yes, add one row per size and use the same Parent Name.
A21: Weights | B21: Weights: every plant currently shows 1 kg / 70 cm (placeholder). Real weight and pot/bag size are needed for delivery and truck-capacity calculation.
A22: GST | B22: GST: please confirm HSN and GST % per product (plants are usually HSN 0602 at 0%, vermicompost/compost 3101 at 5%; confirm with your CA).

Sheet Feature Map
A1: Feature Map
A2: Each website feature and the data needed to build it.
A4: # | B4: Feature | C4: Where on site | D4: SRS ref | E4: What it does | F4: Data needed from Hasiru Agro | G4: Filled in tab | H4: Priority | I4: Status
A5: 1 | B5: Two-path entry (I know what I want / Help me choose) | C5: Home hero | D5: 1.1 | E5: Splits shoppers into direct shop vs guided recommendation. | F5: Banner image, headline copy. | G5: Content & Policies | H5: Must | I5: Pending
A6: 2 | B6: Best sellers carousel (quick-commerce style) | C6: Home | D6: 1.2 | E6: Horizontal swipe cards with add to cart. | F6: Best seller flag, image, height, exposure, rain, temperature, packet weight, price, offer price, availability. | G6: Plants | H6: Must | I6: Pending
A7: 3 | B7: Simple plant calculator (plants per acre) | C7: Home + floating on Shop | D7: 1.2A, 3.4 | E7: 43,560 / (spacing L x W ft) = plants per acre. | F7: Recommended spacing L and W (ft) per plant. Confirm formula and any buffer % (note '43,560 x 3 / 100' in sketch). | G7: Plants, Calculators | H7: Must | I7: Pending
A8: 4 | B8: Input products carousel | C8: Home | D8: 1.3 | E8: Compost, seeds, biochar, liquid fertiliser, bio-pesticide cards. | F8: Full input product list with pack sizes and prices. | G8: Input Products | H8: Must | I8: Pending
A9: 5 | B9: Compost calculator | C9: Home | D9: 1.4 | E9: Plants selected -> estimated compost -> recommended product -> add to cart. | F9: Compost kg per plant (by plant size/type), product to recommend. | G9: Calculators, Plants | H9: Must | I9: Pending
A10: 6 | B10: Incubated by UAS Dharwad band | C10: Home + About | D10: 1.5, 26 | E10: Running band of institutional logos. | F10: Logos (UAS Dharwad, Startup India, MSME, others), approved wording, links. | G10: Content & Policies | H10: Must | I10: Pending
A11: 7 | B11: DIY / Learn how videos | C11: Home + Recommendation page | D11: 1.6, 8 | E11: Video carousel; model-specific planting video. | F11: Video URLs, titles, thumbnails, category, linked model. | G11: Content & Policies | H11: Must | I11: Pending
A12: 8 | B12: Why Choose Us | C12: Home + own page | D12: 1.7, 2, 24 | E12: Authenticity, expertise, results, delivery to farm. | F12: Verified numbers: acres, farms, customers, projects, plants planted. | G12: Content & Policies | H12: Must | I12: Pending
A13: 9 | B13: Testimonials | C13: Home | D13: 1.8 | E13: Horizontal review cards. | F13: Name, location, photo, review, rating, farm/project info. | G13: Content & Policies | H13: Must | I13: Pending
A14: 10 | B14: Plant shop with categories | C14: Shop | D14: 3.1-3.3 | E14: Timber / Fruiting / Other grid with qty +/-. | F14: Final category per plant, description, price, stock, availability. | G14: Plants, Category Map | H14: Must | I14: Pending
A15: 11 | B15: Product attributes | C15: Product page | D15: 1.2, 3.2 | E15: Spec table on each plant. | F15: Height, exposure, rain, temperature, type, bearing time, yield, spacing, harvest season. | G15: Plants | H15: Must | I15: Pending
A16: 12 | B16: Help me choose wizard | C16: Popup | D16: 4.1-4.3 | E16: Land size (acre / sq ft), location (map/search), purpose, name + phone OTP, Generate. | F16: Purposes list (Commercial, Food Forest, Miyawaki, others). Any location-based rules (which plants suit which district/climate). | G16: Recommendation Models | H16: Must | I16: Pending
... A33: 29 | B33: Admin dashboard + inventory | C33: Admin | D33: 30-33 | E33: Sales, regions, best sellers, low stock, enquiries, orders. | F33: Low-stock threshold per product; current stock. | G33: Plants, Input Products | H33: Must | I33: Pending

Sheet Plants
A1: Plants: Product Master
A2: Green = from old shop (please verify). Yellow = please fill. Blue = auto. One row per plant per size.
A4: SKU | B4: Plant Name | C4: Kannada Name | D4: Old Category | E4: New Category | F4: Sub-category | G4: Show on site? | H4: Best Seller? | I4: Plant Type (Grafted / Seeded / Air layered...) | J4: Size / Variant (e.g. 2 ft, 6 ft) | K4: Plant Height at Sale (ft) | L4: Pot / Bag Size | M4: Weight per Plant incl. pot (kg) | N4: Plants per Truck (smallest vehicle) | O4: Regular Price (Rs) | P4: Sale Price (Rs) | Q4: Offline Price (Rs) | R4: Bulk Starts at Qty (e.g. 50 for big trees, 200 for shrubs) | S4: Bulk Price per Plant (Rs) | T4: Current Stock | U4: Low Stock Alert at | V4: Availability | W4: HSN Code | X4: GST % | Y4: Spacing L (ft) | Z4: Spacing W (ft) | AA4: Plants per Acre | AB4: Spacing (old text) | AC4: Exposure | AD4: Rain / Water Need | AE4: Temperature | AF4: Growth Habit | AG4: Bearing Time | AH4: Yield per Tree | AI4: Harvest Season | AJ4: Fruit Size | AK4: Suitable Models (Commercial / Food Forest / Miyawaki) | AL4: Role in Model (Main / Host / Biomass) | AM4: Forest Layer (Canopy / Sub-canopy / Shrub...) | AN4: Vermicompost per Plant (kg) | AO4: Biochar per Plant (kg) | AP4: Compost per Plant (kg) | AQ4: Districts / Zones NOT suitable | AR4: Image URL (old site) | AS4: New Photo Needed? | AT4: Notes / Corrections
A5: HA001 | B5: Guava KG | D5: Desi Fruits | E5: Fruiting Trees | F5: Desi | G5: Yes | H5: No | I5: Air layered | O5: 640 | P5: 450 | Q5: 180 | T5: 0 | V5: Out of Stock | Y5: 18 | Z5: 18 | AA5: =IF(AND(N(Y5)>0,N(Z5)>0),ROUND(43560/(Y5*Z5),0),"") | AB5: 18ft x 18ft | AC5: Full sun | AE5: 20°C to 40 °C | AF5: Medium sized tree | AG5: 2 years | AH5: 350Kg to 400Kg | AI5: Round the year | AJ5: 400gms to 1000gms | AR5: https://hasiruagro.com/wp-content/uploads/2023/08/Guava-KG-Fruit-fruit-image-Hasiruagro.jpg
A6: HA002 | B6: GuavaTaiwan Pink | D6: Desi Fruits | E6: Fruiting Trees | F6: Desi | G6: Yes | H6: No | I6: Air layered | O6: 600 | P6: 420 | Q6: 60 | T6: 0 | V6: Out of Stock | Y6: 18 | Z6: 18 | AA6: =IF(AND(N(Y6)>0,N(Z6)>0),ROUND(43560/(Y6*Z6),0),"") | AB6: 18ft x 18ft | AC6: Full sun | AE6: 20°C to 40 °C | AF6: Medium sized tree | AG6: 2 years | AH6: 30Kg to 70kg | AI6: Round the year | AJ6: 150gms to 200gms | AR6: https://hasiruagro.com/wp-content/uploads/2023/08/taiwan-pink-guava-fruit-fruit-image-Hasiruagro.jpg
A7: HA003 | B7: Abiu (Seeded) | D7: Exotic fruits | E7: Fruiting Trees | F7: Exotic | G7: Yes | H7: No | I7: Seeded | O7: 1560 | P7: 1090 | Q7: 680 | T7: 0 | V7: Out of Stock | AA7: =IF(AND(N(Y7)>0,N(Z7)>0),ROUND(43560/(Y7*Z7),0),"") | AC7: Full sun | AE7: 16°C to 35 °C | AF7: Medium tree | AG7: 2 years | AH7: 100Kgs to 150Kgs | AI7: February to October | AJ7: 300gms to 600gms | AR7: https://hasiruagro.com/wp-content/uploads/2023/08/Abiu-Fruit-Plantplant-with-fruit-image-Hasiruagro.jpg
A8: HA004 | B8: Achachiru | D8: Exotic fruits | E8: Fruiting Trees | F8: Exotic | G8: Yes | H8: No | I8: Grafted | O8: 1540 | P8: 1080 | Q8: 830 | T8: 30 | V8: Available | AA8: =IF(AND(N(Y8)>0,N(Z8)>0),ROUND(43560/(Y8*Z8),0),"") | AC8: Full shade | AE8: 16°C to 35 °C | AF8: Medium tree | AG8: 4 years | AH8: 75Kgs to 150Kgs | AI8: October to May | AJ8: 100gms to 150gms | AR8: https://hasiruagro.com/wp-content/uploads/2023/08/Achachairuplant-with-fruit-image-Hasiruagro.jpg
A9: HA005 | B9: Agarwood | D9: Forestry | E9: Timber Trees | G9: Yes | H9: Yes | I9: Seeded | O9: 400 | P9: 280 | Q9: 60 | T9: 0 | V9: Out of Stock | Y9: 15 | Z9: 15 | AA9: =IF(AND(N(Y9)>0,N(Z9)>0),ROUND(43560/(Y9*Z9),0),"") | AB9: 15ft x 15ft | AC9: Full sun | AE9: 20°C to 35°C | AF9: 20ft to 30ft tall | AG9: 12 years | AH9: 5 to 8 kilograms of heartwood. | AR9: https://hasiruagro.com/wp-content/uploads/2023/07/Agarwood-F.jpg
A10: HA006 | B10: All season Jackfruit | D10: Desi Fruits | E10: Fruiting Trees | F10: Desi | G10: Yes | H10: No | I10: Grafted | O10: 1325 | P10: 530 | Q10: 180 | T10: 0 | V10: Out of Stock | Y10: 20 | Z10: 20 | AA10: =IF(AND(N(Y10)>0,N(Z10)>0),ROUND(43560/(Y10*Z10),0),"") | AB10: 20ft x 20ft | AC10: Open sun | AE10: 20°C to 40 °C | AF10: Big tree | AG10: 2 years | AH10: 150 to 200 fruits | AI10: Round the year | AJ10: Medium to Large | AR10: https://hasiruagro.com/wp-content/uploads/2023/07/All-season-Jackfruit-fruit-image.webp
A11: HA007 | B11: All Season Lemon | D11: Desi Fruits | E11: Fruiting Trees | F11: Desi | G11: Yes | H11: No | I11: Grafted | O11: 440 | P11: 310 | Q11: 150 | T11: 1 | V11: Available | Y11: 10 | Z11: 10 | AA11: =IF(AND(N(Y11)>0,N(Z11)>0),ROUND(43560/(Y11*Z11),0),"") | AB11: 10ft x 10ft | AC11: Open sun | AE11: 20°C to 40 °C | AF11: Small tree | AG11: 2 years | AH11: 80Kg to 100Kg | AI11: Year round | AJ11: 30gms to 50gms | AR11: https://hasiruagro.com/wp-content/uploads/2023/07/All-Season-Lemon-fruit-fruit-ima.webp
A12: HA008 | B12: All Season Mango | D12: Desi Fruits | E12: Fruiting Trees | F12: Desi | G12: Yes | H12: Yes | I12: Grafted | O12: 700 | P12: 490 | Q12: 220 | T12: 0 | V12: Out of Stock | Y12: 18 | Z12: 18 | AA12: =IF(AND(N(Y12)>0,N(Z12)>0),ROUND(43560/(Y12*Z12),0),"") | AB12: 18ft x 18ft | AC12: Open sun | AE12: 20°C to 40 °C | AF12: Medium sized tree | AG12: 2 years | AH12: 200 to 250 fruits | AI12: Year round | AJ12: 100gm to 150gm | AR12: https://hasiruagro.com/wp-content/uploads/2023/08/All-Season-Mango-Fruit-image-Hasiruagro.jpg
A13: HA009 | B13: All spices | D13: Spices | E13: Other Plants | F13: Spices | G13: Yes | H13: Yes | I13: Seeded | O13: 440 | P13: 310 | Q13: 120 | T13: 0 | V13: Out of Stock | AA13: =IF(AND(N(Y13)>0,N(Z13)>0),ROUND(43560/(Y13*Z13),0),"") | AB13: Medium size tree | AC13: Full sun or Partial shade | AE13: 16°C to 35°C | AF13: Medium size tree | AG13: 3 years | AH13: 20-25 Kg dry berries | AI13: June to September | AJ13: 1gm to 2gms | AR13: https://hasiruagro.com/wp-content/uploads/2023/07/All-Spices-F.jpg
A14: HA0010 | B14: Allahabad Safeda Guava | D14: Desi Fruits | E14: Fruiting Trees | F14: Desi | G14: Yes | H14: No | I14: Air layered | O14: 400 | P14: 280 | Q14: 100 | T14: 0 | V14: Out of Stock | Y14: 18 | Z14: 18 | AA14: =IF(AND(N(Y14)>0,N(Z14)>0),ROUND(43560/(Y14*Z14),0),"") | AB14: 18ft x 18ft | AC14: Full sun | AE14: 20°C to 40 °C | AF14: Medium sized tree | AG14: 2 years | AH14: 30Kg to 70kg | AI14: Round the year | AJ14: 150gms to 200gms | AR14: https://hasiruagro.com/wp-content/uploads/2023/08/allahabad-safeda-guava-fruit-fruit-image-Hasiruagro.jpg
A15: HA0011 | B15: Alphonoso Mango | D15: Desi Fruits | E15: Fruiting Trees | F15: Desi | G15: Yes | H15: Yes | I15: Grafted | O15: 700 | P15: 490 | Q15: 350 | T15: 168 | V15: Available | Y15: 18 | Z15: 18 | AA15: =IF(AND(N(Y15)>0,N(Z15)>0),ROUND(43560/(Y15*Z15),0),"") | AB15: 18ft x 18ft | AC15: Open sun | AE15: 20°C to 40 °C | AF15: Medium sized tree | AG15: 2 years | AH15: 300 to 500 fruits | AI15: April to August | AJ15: 200gm to 250gm | AR15: https://hasiruagro.com/wp-content/uploads/2023/08/Alphonso-Mango-S.jpg
A16: HA0012 | B16: American Red Palmar mango | D16: Exotic fruits | E16: Fruiting Trees | F16: Exotic | G16: Yes | H16: Yes | I16: Grafted | O16: 700 | P16: 490 | Q16: 250 | T16: 0 | V16: Out of Stock | AA16: =IF(AND(N(Y16)>0,N(Z16)>0),ROUND(43560/(Y16*Z16),0),"") | AC16: Full sun | AE16: 20°C to 40 °C | AF16: Medium to big tree | AG16: 2 years | AH16: 80Kgs to 100Kgs per tree | AI16: March to June | AJ16: 150gms to 200gms | AR16: https://hasiruagro.com/wp-content/uploads/2023/08/American-Red-Palmar-1.jpg
A17: HA0013 | B17: Amla (Grafted) | D17: Desi Fruits | E17: Fruiting Trees | F17: Desi | G17: Yes | H17: No | I17: Grafted | O17: 900 | P17: 630 | Q17: 250 | T17: 0 | V17: Out of Stock | Y17: 20 | Z17: 20 | AA17: =IF(AND(N(Y17)>0,N(Z17)>0),ROUND(43560/(Y17*Z17),0),"") | AB17: 20ft x 20ft | AC17: Open sun | AE17: 20°C to 40 °C | AF17: Big tree | AG17: 5 yeras | AH17: 50Kg to 70Kg | AI17: September to December | AJ17: 60gm to 70gm | AR17: https://hasiruagro.com/wp-content/uploads/2023/08/Amla-Grafted-fruit-image-Hasiruagro.jpg
A18: HA0014 | B18: Amla (Seeded) | D18: Desi Fruits | E18: Fruiting Trees | F18: Desi | G18: Yes | H18: No | I18: Seeded | O18: 700 | P18: 490 | Q18: 100 | T18: 6 | V18: Available | Y18: 20 | Z18: 20 | AA18: =IF(AND(N(Y18)>0,N(Z18)>0),ROUND(43560/(Y18*Z18),0),"") | AB18: 20ft x 20ft | AC18: Open sun | AE18: 20°C to 40 °C | AF18: Big tree | AG18: 5 yeras | AH18: 50Kg to 70Kg | AI18: September to December | AJ18: 60gm to 70gm | AR18: https://hasiruagro.com/wp-content/uploads/2023/07/Amla-F.jpg
A19: HA0015 | B19: Amrapali Mango | D19: Desi Fruits | E19: Fruiting Trees | F19: Desi | G19: Yes | H19: No | I19: Grafted | O19: 540 | P19: 380 | Q19: 200 | T19: 0 | V19: Out of Stock | Y19: 18 | Z19: 18 | AA19: =IF(AND(N(Y19)>0,N(Z19)>0),ROUND(43560/(Y19*Z19),0),"") | AB19: 18ft x 18ft | AC19: Open sun | AE19: 20°C to 40 °C | AF19: Medium sized tree | AG19: 2 years | AH19: 200 to 250 fruits | AI19: Year round | AJ19: 100gm to 150gm | AR19: https://hasiruagro.com/wp-content/uploads/2023/08/Amrapali-MangoFruit-image-Hasiruagro.jpg
A20: HA0016 | B20: Diana Anjeer Fig Plants | D20: Exotic fruits | E20: Fruiting Trees | F20: Exotic | G20: Yes | H20: No | I20: Grafted | O20: 500 | P20: 350 | Q20: 150 | T20: 0 | V20: Out of Stock | AA20: =IF(AND(N(Y20)>0,N(Z20)>0),ROUND(43560/(Y20*Z20),0),"") | AC20: Full sun | AE20: 20°C to 40 °C | AF20: Medium to big tree | AG20: 2 years | AH20: 180 to 360 fruits per tree | AI20: Febraury to August | AJ20: 50gms to 70gms | AR20: https://hasiruagro.com/wp-content/uploads/2024/03/Diana-Anjeer-Fig-Plants-Hasiruagro.jpg
A21: HA0017 | B21: Appe midi Mango | D21: Desi Fruits | E21: Fruiting Trees | F21: Desi | G21: Yes | H21: No | I21: Grafted | O21: 660 | P21: 460 | Q21: 250 | T21: 0 | V21: Out of Stock | Y21: 18 | Z21: 18 | AA21: =IF(AND(N(Y21)>0,N(Z21)>0),ROUND(43560/(Y21*Z21),0),"") | AB21: 18ft x 18ft | AC21: Open sun | AE21: 20°C to 40 °C | AF21: Medium sized tree | AG21: 2 years | AH21: 300 to 500 fruits | AI21: April to August | AJ21: 50gm to 100gm | AR21: https://hasiruagro.com/wp-content/uploads/2023/08/Appe-Midi-Mango-F.jpg
A22: HA0018 | B22: Apple Ana | D22: Desi Fruits | E22: Fruiting Trees | F22: Desi | G22: Yes | H22: No | I22: Grafted | O22: 560 | P22: 390 | Q22: 180 | T22: 0 | V22: Out of Stock | Y22: 15 | Z22: 15 | AA22: =IF(AND(N(Y22)>0,N(Z22)>0),ROUND(43560/(Y22*Z22),0),"") | AB22: 15ft x 15ft | AC22: Full sun | AE22: 20°C to 30 °C | AF22: Medium sized tree | AG22: 3 years | AH22: 50Kg to 80Kg | AI22: April to July | AJ22: 80gms to 120gms | AR22: https://hasiruagro.com/wp-content/uploads/2023/08/Apple-AnaFruit-image-Hasiruagro.jpg
A23: HA0019 | B23: Apple Ber Ball sundari | D23: Exotic fruits | E23: Fruiting Trees | F23: Exotic | G23: Yes | H23: No | I23: Seeded | O23: 280 | P23: 195 | Q23: 60 | T23: 47 | V23: Available | AA23: =IF(AND(N(Y23)>0,N(Z23)>0),ROUND(43560/(Y23*Z23),0),"") | AC23: Full sun | AE23: 20°C to 40 °C | AF23: Small Tree | AG23: 3 years | AH23: 50Kgs to 70Kgs per tree | AI23: Alternative seasons | AJ23: 50gms to 70gms | AR23: https://hasiruagro.com/wp-content/uploads/2023/08/Apple-Ber-Ball-sundariPlant-with-Fruit-image-Hasiruagro.jpg
A24: HA0020 | B24: Apple Ber Kashmiri | D24: Exotic fruits | E24: Fruiting Trees | F24: Exotic | G24: Yes | H24: No | I24: Seeded | O24: 280 | P24: 195 | Q24: 60 | T24: 47 | V24: Available | AA24: =IF(AND(N(Y24)>0,N(Z24)>0),ROUND(43560/(Y24*Z24),0),"") | AC24: Full sun | AE24: 20°C to 40 °C | AF24: Small Tree | AG24: 3 years | AH24: 50Kgs to 70Kgs per tree | AI24: Alternative seasons | AJ24: 50gms to 70gms | AR24: https://hasiruagro.com/wp-content/uploads/2023/08/Apple-Ber-KashmiriPlant-with-Fruit-image-Hasiruagro.jpg
A25: HA0021 | B25: Apple Dorset | D25: Desi Fruits | E25: Fruiting Trees | F25: Desi | G25: Yes | H25: No | I25: Grafted | O25: 560 | P25: 390 | Q25: 180 | T25: 0 | V25: Out of Stock | Y25: 15 | Z25: 15 | AA25: =IF(AND(N(Y25)>0,N(Z25)>0),ROUND(43560/(Y25*Z25),0),"") | AB25: 15ft x 15ft | AC25: Full sun | AE25: 18°C to 35 °C | AF25: Medium sized tree | AG25: 3 years | AH25: 50Kg to 80Kg | AI25: April to July | AJ25: 80gms to 120gms | AR25: https://hasiruagro.com/wp-content/uploads/2023/08/Apple-DorsetFruit-image-Hasiruagro.jpg
A26: HA0022 | B26: Apple Hariman-99 | D26: Desi Fruits | E26: Fruiting Trees | F26: Desi | G26: Yes | H26: No | I26: Grafted | O26: 600 | P26: 420 | Q26: 450 | T26: 0 | V26: Out of Stock | Y26: 15 | Z26: 15 | AA26: =IF(AND(N(Y26)>0,N(Z26)>0),ROUND(43560/(Y26*Z26),0),"") | AB26: 15ft x 15ft | AC26: Full sun | AE26: 20°C to 35 °C | AF26: Medium sized tree | AG26: 3 years | AH26: 50Kg to 100Kg | AI26: April to July | AJ26: 80gms to 120gms | AR26: https://hasiruagro.com/wp-content/uploads/2023/08/Hariman-Apple-F.jpg
A27: HA0023 | B27: Apple litchi | D27: Desi Fruits | E27: Fruiting Trees | F27: Desi | G27: Yes | H27: No | I27: Grafted | O27: 600 | P27: 420 | Q27: 200 | T27: 0 | V27: Out of Stock | Y27: 25 | Z27: 25 | AA27: =IF(AND(N(Y27)>0,N(Z27)>0),ROUND(43560/(Y27*Z27),0),"") | AB27: 25ft x 25ft | AC27: Full sun | AE27: 15°C to 38°C | AF27: Medium sized tree | AG27: 3 years | AH27: 80Kg to 150Kg | AI27: April to July | AJ27: 50gms to 70gms | AR27: https://hasiruagro.com/wp-content/uploads/2023/08/Apple-litchiFruit-image-Hasiruagro.jpg
A28: HA0024 | B28: Apricot | D28: Exotic fruits | E28: Fruiting Trees | F28: Exotic | G28: Yes | H28: No | I28: Grafted | O28: 700 | P28: 490 | Q28: 250 | T28: 0 | V28: Out of Stock | AA28: =IF(AND(N(Y28)>0,N(Z28)>0),ROUND(43560/(Y28*Z28),0),"") | AC28: Full sun | AE28: 16°C to 35 °C | AF28: Medium to big tree | AG28: 4 years | AH28: 70Kgs to 90Kgs per tree | AI28: April to August | AJ28: 70gms to 100gms | AR28: https://hasiruagro.com/wp-content/uploads/2023/08/ApricotPlant-with-Fruit-image-Hasiruagro.jpg
A29: HA0025 | B29: Areca Bukkambudi | D29: Plantation | E29: Other Plants | F29: Plantation | G29: Yes | H29: No | I29: Seeded | O29: 320 | P29: 225 | Q29: 60 | T29: 348 | V29: Available | Y29: 11 | Z29: 11 | AA29: =IF(AND(N(Y29)>0,N(Z29)>0),ROUND(43560/(Y29*Z29),0),"") | AB29: 11ft x 11ft | AC29: Full sun | AE29: 20°C to 35°C | AF29: 40ft to 60ft | AG29: 4 years | AH29: 200 to 400 ripe nuts | AI29: Alternative seasonsAugust and September in plain land regions and in malnad areas during December and January. | AR29: https://hasiruagro.com/wp-content/uploads/2023/08/Areca-BukkambudiFruit-image-Hasiruagro.jpg
A30: HA0026 | B30: Areca Tirthalli | D30: Plantation | E30: Other Plants | F30: Plantation | G30: Yes | H30: No | I30: Seeded | O30: 320 | P30: 225 | Q30: 60 | T30: 68 | V30: Available | Y30: 11 | Z30: 11 | AA30: =IF(AND(N(Y30)>0,N(Z30)>0),ROUND(43560/(Y30*Z30),0),"") | AB30: 11ft x 11ft | AC30: Full sun | AE30: 20°C to 35°C | AF30: 40ft to 60ft | AG30: 4 years | AH30: 200 to 400 ripe nuts | AI30: Alternative seasonsAugust and September in plain land regions and in malnad areas during December and January. | AR30: https://hasiruagro.com/wp-content/uploads/2023/08/Areca-TirthalliFruit-image-Hasiruagro.jpg
A31: HA0027 | B31: Avocado coorg variety | D31: Exotic fruits | E31: Fruiting Trees | F31: Exotic | G31: Yes | H31: No | I31: Grafted | O31: 875 | P31: 350 | Q31: 150 | T31: 0 | V31: Out of Stock | Y31: 18 | Z31: 18 | AA31: =IF(AND(N(Y31)>0,N(Z31)>0),ROUND(43560/(Y31*Z31),0),"") | AB31: 18ft x 18ft | AC31: Full sun (Can tolerate partial shade | AE31: 16⁰C – 42⁰C | AF31: Medium to large tree (30ft to 60ft tall) | AG31: 2.5 years after planting | AH31: 30Kgs to 50Kgs | AI31: June to October | AJ31: 150gms to 250gms | AR31: https://hasiruagro.com/wp-content/uploads/2023/07/Avocado-coorg-varietyFruit-image-Hasiruagro.webp
A32: HA0028 | B32: Hass Avocado Plant | D32: Exotic fruits | E32: Fruiting Trees | F32: Exotic | G32: Yes | H32: No | I32: Grafted | O32: 2800 | P32: 1120 | Q32: 700 | T32: 0 | V32: Out of Stock | Y32: 18 | Z32: 18 | AA32: =IF(AND(N(Y32)>0,N(Z32)>0),ROUND(43560/(Y32*Z32),0),"") | AB32: 18ft x 18ft | AC32: Full sun (Can tolerate partial shade | AE32: 16⁰C – 35⁰C | AF32: Medium to large tree (30ft to 60ft tall) | AG32: 2.5 years after planting | AH32: 120 Kgs to160 Kgs | AI32: June to Otober | AJ32: 150gms to 250gms | AR32: https://hasiruagro.com/wp-content/uploads/2023/07/avocado-haas-fruit-fruit-image-Hasiruagro.webp
A33: HA0029 | B33: Grafted Mexican Purple Avocado Plant | D33: Exotic fruits | E33: Fruiting Trees | F33: Exotic | G33: Yes | H33: No | I33: Grafted | O33: 1575 | P33: 630 | Q33: 350 | T33: 0 | V33: Out of Stock | Y33: 18 | Z33: 18 | AA33: =IF(AND(N(Y33)>0,N(Z33)>0),ROUND(43560/(Y33*Z33),0),"") | AB33: 18ft x 18ft | AC33: Full sun (Can tolerate partial shade | AE33: 20⁰C – 42⁰C | AF33: Medium to large tree (30ft to 60ft tall) | AG33: 2.5 years after planting | AH33: 180kgs to 200kgs | AI33: June to October | AJ33: 200gms to 300gms | AR33: https://hasiruagro.com/wp-content/uploads/2023/07/Grafted-Mexican-Purple-Avocado-Hasiruagro.webp
A34: HA0030 | B34: Shiny green Avocado | D34: Exotic fruits | E34: Fruiting Trees | F34: Exotic | G34: Yes | H34: No | I34: Grafted | O34: 1575 | P34: 630 | Q34: 350 | T34: 0 | V34: Out of Stock | Y34: 18 | Z34: 18 | AA34: =IF(AND(N(Y34)>0,N(Z34)>0),ROUND(43560/(Y34*Z34),0),"") | AB34: Spacing: 18ft x 18ft | AC34: Full sun (Can tolerate partial shade | AE34: 16°C to 40°C | AF34: Growth: Medium to large tree (30ft to 60ft tall) | AG34: 2.5 years after planting | AH34: 180Kgs to 200Kgs | AI34: Harvesting: June to October | AJ34: 150gms to 250gms | AR34: https://hasiruagro.com/wp-content/uploads/2023/07/Grafted-Shiny-Green-Avocado-Hasiruagro.webp
A35: HA0031 | B35: Avocado TKD-1 | D35: Exotic fruits | E35: Fruiting Trees | F35: Exotic | G35: Yes | H35: No | I35: Grafted | O35: 1575 | P35: 630 | Q35: 350 | T35: 0 | V35: Out of Stock | Y35: 18 | Z35: 18 | AA35: =IF(AND(N(Y35)>0,N(Z35)>0),ROUND(43560/(Y35*Z35),0),"") | AB35: 18ft x 18ft | AC35: Full sun (Can tolerate partial shade | AE35: 16⁰C – 35⁰C | AF35: Medium to large tree (30ft to 60ft tall) | AG35: 2.5 years after planting | AH35: 250 Kgs to300 Kgs | AI35: June to Otober | AJ35: 150gms to 250gms | AR35: https://hasiruagro.com/wp-content/uploads/2023/07/Avocado-TKD-1Fruit-image-Hasiruagro.webp
A36: HA0032 | B36: B-1 Musambi Malta | D36: Desi Fruits | E36: Fruiting Trees | F36: Desi | G36: Yes | H36: No | I36: Grafted | O36: 500 | P36: 350 | Q36: 200 | T36: 250 | V36: Available | Y36: 18 | Z36: 18 | AA36: =IF(AND(N(Y36)>0,N(Z36)>0),ROUND(43560/(Y36*Z36),0),"") | AB36: 18ft x 18ft | AC36: Open sun | AE36: 20°C to 40 °C | AF36: Medium sized tree | AG36: 2 years | AH36: 60Kg to 100Kg | AI36: April to MayAugust to September | AJ36: 70 gm to 150gm | AR36: https://hasiruagro.com/wp-content/uploads/2023/08/B-1-Musambi-MaltaFruit-image-Hasiruagro.jpg
A37: HA0033 | B37: Badami Mango | D37: Desi Fruits | E37: Fruiting Trees | F37: Desi | G37: Yes | H37: No | I37: Grafted | O37: 700 | P37: 490 | Q37: 250 | T37: 122 | V37: Available | Y37: 18 | Z37: 18 | AA37: =IF(AND(N(Y37)>0,N(Z37)>0),ROUND(43560/(Y37*Z37),0),"") | AB37: 18ft x 18ft | AC37: Open sun | AE37: 20°C to 40 °C | AF37: Medium sized tree | AG37: 2 years | AH37: 300 to 500 fruits | AI37: April to August | AJ37: 200gm to 250gm | AR37: https://hasiruagro.com/wp-content/uploads/2023/08/Mango-Badami-Fruit-fruit-image-Hasiruagro.jpg
A38: HA0034 | B38: Banana Sapota | D38: Exotic fruits | E38: Fruiting Trees | F38: Exotic | G38: Yes | H38: No | I38: Grafted | O38: 1400 | P38: 980 | Q38: 200 | T38: 0 | V38: Out of Stock | AA38: =IF(AND(N(Y38)>0,N(Z38)>0),ROUND(43560/(Y38*Z38),0),"") | AC38: Full sun | AE38: 20°C to 40 °C | AF38: Medium to big tree | AG38: 3 years | AH38: 2500 to 3000 fruits per tree | AI38: Alternate seasons | AJ38: 150gms to 200gms | AR38: https://hasiruagro.com/wp-content/uploads/2023/08/banana-sapota-fruit-fruit-image-Hasiruagro.jpg
A39: HA0035 | B39: Bangkok Mango | D39: Exotic fruits | E39: Fruiting Trees | F39: Exotic | G39: Yes | H39: No | I39: Grafted | O39: 800 | P39: 560 | Q39: 200 | T39: 0 | V39: Out of Stock | AA39: =IF(AND(N(Y39)>0,N(Z39)>0),ROUND(43560/(Y39*Z39),0),"") | AC39: Full sun | AE39: 20°C to 35°C | AF39: Small to medium sized tree | AG39: 3 years | AH39: 100Kgs to 150Kgs per tree | AI39: March to June | AJ39: 500gm to 700gm | AR39: https://hasiruagro.com/wp-content/uploads/2023/08/Bangkok-Mango.jpg
A40: HA0036 | B40: Barbados Cherry | D40: Exotic fruits | E40: Fruiting Trees | F40: Exotic | G40: Yes | H40: No | I40: Seeded | O40: 560 | P40: 390 | Q40: 180 | T40: 0 | V40: Out of Stock | AA40: =IF(AND(N(Y40)>0,N(Z40)>0),ROUND(43560/(Y40*Z40),0),"") | AC40: Full sun | AE40: 16°C to 35 °C | AF40: Small tree | AG40: 3 years | AH40: 20Kgs to 30Kgs per tree | AI40: November to March | AJ40: 70gms to 100gms | AR40: https://hasiruagro.com/wp-content/uploads/2023/08/Barbados-CherryFruit-image-Hasiruagro.jpg
A41: HA0037 | B41: Bhadoli Jamun | D41: Desi Fruits | E41: Fruiting Trees | F41: Desi | G41: Yes | H41: No | O41: 450 | P41: 315 | Q41: 150 | T41: 0 | V41: Out of Stock | Y41: 20 | Z41: 20 | AA41: =IF(AND(N(Y41)>0,N(Z41)>0),ROUND(43560/(Y41*Z41),0),"") | AB41: 20ft x 20ft | AC41: Open sun | AE41: 20°C to 40 °C | AF41: Big tree | AG41: 2 years | AH41: 60Kg to 70Kg | AI41: May to August | AJ41: 50gm to 100gm | AR41: https://hasiruagro.com/wp-content/uploads/2023/08/Bhadoli-JamunFruit-image-Hasiruagro.jpg
A42: HA0038 | B42: Bhima Bamboo | D42: Forestry | E42: Timber Trees | G42: Yes | H42: No | I42: Stem cuttings | O42: 360 | P42: 250 | Q42: 80 | T42: 0 | V42: Out of Stock | Y42: 15 | Z42: 15 | AA42: =IF(AND(N(Y42)>0,N(Z42)>0),ROUND(43560/(Y42*Z42),0),"") | AB42: 15ft x 15ft | AC42: Full sun | AE42: 20°C to 40°C | AF42: 20ft to 30 ft tall | AG42: 5 to 6 years | AR42: https://hasiruagro.com/wp-content/uploads/2023/08/Bhima-Bamboo.jpg
A43: HA0039 | B43: Bhutan Chatuki Orange | D43: Exotic fruits | E43: Fruiting Trees | F43: Exotic | G43: Yes | H43: No | I43: Grafted | O43: 560 | P43: 390 | Q43: 180 | T43: 0 | V43: Out of Stock | AA43: =IF(AND(N(Y43)>0,N(Z43)>0),ROUND(43560/(Y43*Z43),0),"") | AC43: Full sun | AE43: 16°C to 35 °C | AF43: Medium tree | AG43: 2 years | AH43: 250 to 350 oranges per tree | AI43: Year round | AJ43: 80gms to 150gms | AR43: https://hasiruagro.com/wp-content/uploads/2023/07/Bhutan-Chatuki-Orange.webp
A44: HA0040 | B44: Black mango | D44: Exotic fruits | E44: Fruiting Trees | F44: Exotic | G44: Yes | H44: No | I44: Grafted | O44: 800 | P44: 560 | Q44: 300 | V44: Out of Stock | AA44: =IF(AND(N(Y44)>0,N(Z44)>0),ROUND(43560/(Y44*Z44),0),"") | AC44: Full sun | AE44: 20°C to 35°C | AF44: Small to medium sized tree | AG44: 3 years | AH44: 100Kgs to 150Kgs per tree | AI44: Throughout the year | AJ44: 400gm to 500gm | AR44: https://hasiruagro.com/wp-content/uploads/2023/07/Black-Mango.jpg
A45: HA0041 | B45: Black guava | D45: Exotic fruits | E45: Fruiting Trees | F45: Exotic | G45: Yes | H45: No | I45: Air layered | O45: 500 | P45: 350 | Q45: 150 | T45: 33 | V45: Available | AA45: =IF(AND(N(Y45)>0,N(Z45)>0),ROUND(43560/(Y45*Z45),0),"") | AC45: Full sun | AE45: 20°C to 40 °C | AF45: Medium sized tree | AG45: 2 years | AH45: 60Kgs to 150Kgs per tree | AI45: Year round | AJ45: 20gm to 50gm | AR45: https://hasiruagro.com/wp-content/uploads/2023/08/Black-guava-fruit-image-Hasiruagro.jpg
A46: HA0042 | B46: Bombay litchi | D46: Desi Fruits | E46: Fruiting Trees | F46: Desi | G46: Yes | H46: No | I46: Grafted | O46: 500 | P46: 350 | Q46: 150 | T46: 0 | V46: Out of Stock | Y46: 25 | Z46: 25 | AA46: =IF(AND(N(Y46)>0,N(Z46)>0),ROUND(43560/(Y46*Z46),0),"") | AB46: 25ft x 25ft | AC46: Full sun | AE46: 15°C to 38°C | AF46: Medium sized tree | AG46: 3 years | AH46: 80Kg to 150Kg | AI46: April to July | AJ46: 50gms to 70gms | AR46: https://hasiruagro.com/wp-content/uploads/2023/08/Bombay-litchi.jpg
A47: HA0043 | B47: Bread fruit | D47: Exotic fruits | E47: Fruiting Trees | F47: Exotic | G47: Yes | H47: No | I47: Seeded | O47: 900 | P47: 630 | Q47: 350 | T47: 0 | V47: Out of Stock | AA47: =IF(AND(N(Y47)>0,N(Z47)>0),ROUND(43560/(Y47*Z47),0),"") | AC47: Full sun | AE47: 20°C to 35°C | AF47: Big tree | AG47: 5 years | AH47: 150 to 250 fruits per tree | AI47: June to September | AJ47: 1Kg to 5Kg | AR47: https://hasiruagro.com/wp-content/uploads/2023/08/Bread-fruit.jpg
A48: HA0044 | B48: Byrachandra Jackfruit | D48: Desi Fruits | E48: Fruiting Trees | F48: Desi | G48: Yes | H48: No | I48: Grafted | O48: 1225 | P48: 490 | Q48: 260 | T48: 0 | V48: Out of Stock | Y48: 20 | Z48: 20 | AA48: =IF(AND(N(Y48)>0,N(Z48)>0),ROUND(43560/(Y48*Z48),0),"") | AB48: 20ft x 20ft | AC48: Open sun | AE48: 20°C to 40 °C | AF48: Big tree | AG48: 2 years | AH48: 150 to 200 fruits | AI48: July to December | AJ48: Medium to Large | AR48: https://hasiruagro.com/wp-content/uploads/2023/08/Byrachandra-Jackfruit-F.jpg
A49: HA0045 | B49: Cardamom(Vijetha) | D49: Spices | E49: Other Plants | F49: Spices | G49: Yes | H49: No | I49: Root suckers | O49: 320 | P49: 225 | Q49: 60 | T49: 0 | V49: Out of Stock | AA49: =IF(AND(N(Y49)>0,N(Z49)>0),ROUND(43560/(Y49*Z49),0),"") | AB49: Small bushy plant | AC49: Full shade | AE49: 10°C to 35°C | AF49: Small bushy plant | AG49: 3 years | AH49: 200 - 250 Dry capsules per acre | AI49: September to February | AJ49: 1gm to 2gms | AR49: https://hasiruagro.com/wp-content/uploads/2023/08/CardamomVijetha-fruit-image-Hasiruagro.jpg
A50: HA0046 | B50: Chikku (Cricket ball) | D50: Desi Fruits | E50: Fruiting Trees | F50: Desi | G50: Yes | H50: No | I50: Grafted | O50: 520 | P50: 365 | Q50: 180 | T50: 93 | V50: Available | Y50: 18 | Z50: 18 | AA50: =IF(AND(N(Y50)>0,N(Z50)>0),ROUND(43560/(Y50*Z50),0),"") | AB50: 18ft x 18ft | AC50: Open sun | AE50: 20°C to 40 °C | AF50: Medium sized tree | AG50: 2 years | AH50: 1000 to 1500 fruits | AI50: July to NovemberFebruary to March | AJ50: 70 gm to 150gm | AR50: https://hasiruagro.com/wp-content/uploads/2023/08/chikoo-cricket-ball-fruit-fruit-image-Hasiruagro.jpg
A51: HA0047 | B51: Chikku (kalapatti) | D51: Desi Fruits | E51: Fruiting Trees | F51: Desi | G51: Yes | H51: No | I51: Grafted | O51: 520 | P51: 365 | Q51: 180 | T51: 398 | V51: Available | Y51: 18 | Z51: 18 | AA51: =IF(AND(N(Y51)>0,N(Z51)>0),ROUND(43560/(Y51*Z51),0),"") | AB51: 18ft x 18ft | AC51: Open sun | AE51: 20°C to 40 °C | AF51: Medium sized tree | AG51: 2 years | AH51: 1000 to 1500 fruits | AI51: July to NovemberFebruary to March | AJ51: 70 gm to 150gm | AR51: https://hasiruagro.com/wp-content/uploads/2023/08/kalapatti-chikoo-fruit-fruit-image-Hasiruagro.jpg
A52: HA0048 | B52: China Orange | D52: Exotic fruits | E52: Fruiting Trees | F52: Exotic | G52: Yes | H52: No | I52: Grafted | O52: 500 | P52: 350 | Q52: 150 | T52: 15 | V52: Available | AA52: =IF(AND(N(Y52)>0,N(Z52)>0),ROUND(43560/(Y52*Z52),0),"") | AC52: Full sun | AE52: 20°C to 40 °C | AF52: Medium tree | AG52: 2 years | AH52: 250 to 350 oranges per tree | AI52: Year round | AJ52: 80gms to 150gms | AR52: https://hasiruagro.com/wp-content/uploads/2023/07/China-OrangeFruit-image-Hasiruagro.webp
A53: HA0049 | B53: Cinnamon | D53: Spices | E53: Other Plants | F53: Spices | G53: Yes | H53: No | I53: Seeded | O53: 320 | P53: 225 | Q53: 60 | T53: 0 | V53: Out of Stock | AA53: =IF(AND(N(Y53)>0,N(Z53)>0),ROUND(43560/(Y53*Z53),0),"") | AB53: Small tree | AC53: Full sun or Partial shade | AE53: 16°C to 35°C | AF53: Small tree | AG53: 8 to 10 years | AH53: 200Kgs to 250Kgs | AI53: September to November | AJ53: (Bark size)3cms to 5cms | AR53: https://hasiruagro.com/wp-content/uploads/2023/08/Cinnamon-F.jpg
A54: HA0050 | B54: Clove | D54: Spices | E54: Other Plants | F54: Spices | G54: Yes | H54: No | I54: Seeded | O54: 320 | P54: 225 | Q54: 60 | T54: 0 | V54: Out of Stock | AA54: =IF(AND(N(Y54)>0,N(Z54)>0),ROUND(43560/(Y54*Z54),0),"") | AB54: Medium tree | AC54: Full shade | AE54: 16°C to 35°C | AF54: Medium tree | AG54: 3 years | AH54: 4Kgs to 8Kgs | AI54: September to February | AJ54: 2gms to 4gms | AR54: https://hasiruagro.com/wp-content/uploads/2023/08/Clove-F.jpg
A55: HA0051 | B55: Cocoa | D55: Plantation | E55: Other Plants | F55: Plantation | G55: Yes | H55: No | I55: Seeded | O55: 260 | P55: 180 | Q55: 30 | T55: 0 | V55: Out of Stock | Y55: 20 | Z55: 20 | AA55: =IF(AND(N(Y55)>0,N(Z55)>0),ROUND(43560/(Y55*Z55),0),"") | AB55: 20ft x 20ft | AC55: Partial shade | AE55: 20°C to 35°C | AF55: 40ft to 60ft | AG55: 4 years | AH55: 30 to 60 pods per year | AI55: September to December | AR55: https://hasiruagro.com/wp-content/uploads/2023/08/Cocoa.jpg
A56: HA0052 | B56: Coconut Channaraypatna | D56: Plantation | E56: Other Plants | F56: Plantation | G56: Yes | H56: No | I56: Seeded | O56: 700 | P56: 490 | Q56: 250 | T56: 0 | V56: Out of Stock | Y56: 25 | Z56: 25 | AA56: =IF(AND(N(Y56)>0,N(Z56)>0),ROUND(43560/(Y56*Z56),0),"") | AB56: 25ft x 25ft | AC56: Full sun | AE56: 20°C to 35°C | AF56: 40ft to 60ft | AG56: 4 years | AH56: 50 to 100 nuts per year | AI56: Year round | AR56: https://hasiruagro.com/wp-content/uploads/2023/08/Coconut-channarayapatna-fruit-fruit-image-Hasiruagro.jpg
A57: HA0053 | B57: Coconut Tiptur Tall | D57: Plantation | E57: Other Plants | F57: Plantation | G57: Yes | H57: No | I57: Seeded | O57: 600 | P57: 420 | Q57: 200 | T57: 0 | V57: Out of Stock | Y57: 25 | Z57: 25 | AA57: =IF(AND(N(Y57)>0,N(Z57)>0),ROUND(43560/(Y57*Z57),0),"") | AB57: 25ft x 25ft | AC57: Full sun | AE57: 20°C to 35°C | AF57: 40ft to 60ft | AG57: 4 years | AH57: 50 to 100 nuts per year | AI57: Year round | AR57: https://hasiruagro.com/wp-content/uploads/2023/08/Coconut-Tiptur-Tall.jpg
A58: HA0054 | B58: Coffee (Robusta) | D58: Plantation | E58: Other Plants | F58: Plantation | G58: Yes | H58: No | I58: Seeded | O58: 260 | P58: 180 | Q58: 30 | T58: 0 | V58: Out of Stock | Y58: 10 | Z58: 10 | AA58: =IF(AND(N(Y58)>0,N(Z58)>0),ROUND(43560/(Y58*Z58),0),"") | AB58: 10ft x 10ft | AC58: Partial shade | AE58: 20°C to 35°C | AF58: 5ft to 6ft | AG58: 4 years | AH58: 2Kgs to 3Kgs | AI58: Alternative seasonsAugust and September in plain land regions and in malnad areas during December and January. | AR58: https://hasiruagro.com/wp-content/uploads/2023/08/Coffee-Robusta.jpg
A59: HA0055 | B59: Custard apple | D59: Desi Fruits | E59: Fruiting Trees | F59: Desi | G59: Yes | H59: No | I59: Grafted | O59: 400 | P59: 280 | Q59: 100 | T59: 0 | V59: Out of Stock | Y59: 18 | Z59: 18 | AA59: =IF(AND(N(Y59)>0,N(Z59)>0),ROUND(43560/(Y59*Z59),0),"") | AB59: 18ft x 18ft | AC59: Open sun | AE59: 20°C to 40 °C | AF59: Medium sized tree | AG59: 2 years | AH59: 60Kg to 100Kg | AI59: April to MayAugust to September | AJ59: 150 gm to 350gm | AR59: https://hasiruagro.com/wp-content/uploads/2023/08/Custard-Apple-F.jpg
A60: HA0056 | B60: Dang Surya Jackfruit | D60: Desi Fruits | E60: Fruiting Trees | F60: Desi | G60: Yes | H60: No | I60: Grafted | O60: 1225 | P60: 490 | Q60: 260 | T60: 0 | V60: Out of Stock | Y60: 20 | Z60: 20 | AA60: =IF(AND(N(Y60)>0,N(Z60)>0),ROUND(43560/(Y60*Z60),0),"") | AB60: 20ft x 20ft | AC60: Open sun | AE60: 20°C to 40 °C | AF60: Big tree | AG60: 2 years | AH60: 150 to 200 fruits | AI60: July to December | AJ60: Medium to Large | AR60: https://hasiruagro.com/wp-content/uploads/2023/07/Dang-Suriya-F-Jackfruit.webp
A61: HA0057 | B61: Darjeeling orange | D61: Desi Fruits | E61: Fruiting Trees | F61: Desi | G61: Yes | H61: No | O61: 500 | P61: 350 | Q61: 150 | T61: 24 | V61: Available | Y61: 18 | Z61: 18 | AA61: =IF(AND(N(Y61)>0,N(Z61)>0),ROUND(43560/(Y61*Z61),0),"") | AB61: 18ft x 18ft | AC61: Open sun | AE61: 15°C to 35 °C | AF61: Small tree | AG61: 2 years | AH61: 300 to 500 fruits | AI61: September to February | AJ61: 50gm to 100gm | AR61: https://hasiruagro.com/wp-content/uploads/2023/07/Darjeeling-orange.webp
A62: HA0058 | B62: Dasheri Mango | D62: Desi Fruits | E62: Fruiting Trees | F62: Desi | G62: Yes | H62: No | I62: Grafted | O62: 700 | P62: 490 | Q62: 300 | T62: 0 | V62: Out of Stock | Y62: 18 | Z62: 18 | AA62: =IF(AND(N(Y62)>0,N(Z62)>0),ROUND(43560/(Y62*Z62),0),"") | AB62: 18ft x 18ft | AC62: Open sun | AE62: 20°C to 40 °C | AF62: Medium sized tree | AG62: 2 years | AH62: 300 to 500 fruits | AI62: April to August | AJ62: 100gm to 150gm | AR62: https://hasiruagro.com/wp-content/uploads/2023/08/Dasheri-Mango-Fruit-fruit-image-Hasiruagro.jpg
A63: HA0059 | B63: Date Palm | D63: Exotic fruits | E63: Fruiting Trees | F63: Exotic | G63: Yes | H63: No | I63: Seeded | O63: 700 | P63: 490 | Q63: 250 | T63: 0 | V63: Out of Stock | AA63: =IF(AND(N(Y63)>0,N(Z63)>0),ROUND(43560/(Y63*Z63),0),"") | AC63: Full sun | AE63: 20°C to 40 °C | AF63: Big tree | AG63: 5 years | AH63: 100Kgs to 125Kgs per tree | AI63: May to September | AJ63: 70gms to 100gms | AR63: https://hasiruagro.com/wp-content/uploads/2023/08/Date-Palm.jpg
A64: HA0060 | B64: Sweet Red Dragonfruit Plants - Jumbo | D64: Exotic fruits | E64: Fruiting Trees | F64: Exotic | G64: Yes | H64: No | I64: Stem cuttings | O64: 360 | P64: 250 | Q64: 80 | T64: 0 | V64: Out of Stock | Y64: 11 | Z64: 7 | AA64: =IF(AND(N(Y64)>0,N(Z64)>0),ROUND(43560/(Y64*Z64),0),"") | AB64: 11ft x 7ft | AC64: Full sun | AE64: 25°C to 40°C | AF64: Creeper/Climber | AG64: 14 months from planting | AH64: 35Kg-40Kg | AI64: June - December | AJ64: 400gm to 650gm | AR64: https://hasiruagro.com/wp-content/uploads/2024/03/Sweet-Red-Dragonfruit-plants-Jumbo-Hasiruagro.jpg
A65: HA0061 | B65: Dragon fruit Pink | D65: Exotic fruits | E65: Fruiting Trees | F65: Exotic | G65: Yes | H65: No | I65: Stem cuttings | O65: 320 | P65: 225 | Q65: 60 | T65: 0 | V65: Out of Stock | Y65: 11 | Z65: 7 | AA65: =IF(AND(N(Y65)>0,N(Z65)>0),ROUND(43560/(Y65*Z65),0),"") | AB65: 11ft x 7ft | AC65: Full sun | AE65: 25°C to 40°C | AF65: Creeper/Climber | AG65: 14 months from planting | AH65: 25Kg-30Kg | AI65: June - December | AJ65: 150gm to 350gm | AR65: https://hasiruagro.com/wp-content/uploads/2023/08/Dragon-fruit-PinkFruit-image-Hasiruagro.jpg
A66: HA0062 | B66: Dragon fruit White | D66: Exotic fruits | E66: Fruiting Trees | F66: Exotic | G66: Yes | H66: No | I66: Stem cuttings | O66: 300 | P66: 210 | Q66: 50 | T66: 0 | V66: Out of Stock | Y66: 11 | Z66: 7 | AA66: =IF(AND(N(Y66)>0,N(Z66)>0),ROUND(43560/(Y66*Z66),0),"") | AB66: 11ft x 7ft | AC66: Full sun | AE66: 25°C to 40°C | AF66: Creeper/Climber | AG66: 14 months from planting | AH66: 35Kg-40Kg | AI66: June - December | AJ66: 250gm to 500gm | AR66: https://hasiruagro.com/wp-content/uploads/2023/08/Dragon-Fruit-F.jpg
A67: HA0063 | B67: Early dwarf white Jamun | D67: Exotic fruits | E67: Fruiting Trees | F67: Exotic | G67: Yes | H67: No | I67: Grafted | O67: 500 | P67: 350 | Q67: 150 | T67: 69 | V67: Available | AA67: =IF(AND(N(Y67)>0,N(Z67)>0),ROUND(43560/(Y67*Z67),0),"") | AC67: Full sun | AE67: 20°C to 40 °C | AF67: Medium to big tree | AG67: 2 years | AH67: 60Kgs to 70Kgs | AI67: June to July | AJ67: 200gms to 300gms | AR67: https://hasiruagro.com/wp-content/uploads/2023/08/Early-dwarf-white-Jamun.jpg
A68: HA0064 | B68: Egg fruit | D68: Exotic fruits | E68: Fruiting Trees | F68: Exotic | G68: Yes | H68: No | I68: Seeded | O68: 500 | P68: 350 | Q68: 200 | T68: 0 | V68: Out of Stock | AA68: =IF(AND(N(Y68)>0,N(Z68)>0),ROUND(43560/(Y68*Z68),0),"") | AC68: Full sun | AE68: 20°C to 35°C | AF68: Small to medium sized tree | AG68: 4 years | AH68: 40Kgs to 80Kgs per tree | AI68: May to August | AJ68: 50gm to 100gm | AR68: https://hasiruagro.com/wp-content/uploads/2023/08/Egg-Fruit-F.jpg
A69: HA0065 | B69: Finger lime | D69: Exotic fruits | E69: Fruiting Trees | F69: Exotic | G69: Yes | H69: No | I69: Seeded | O69: 600 | P69: 420 | Q69: 200 | T69: 0 | V69: Out of Stock | AA69: =IF(AND(N(Y69)>0,N(Z69)>0),ROUND(43560/(Y69*Z69),0),"") | AC69: Partial shade | AE69: 20°C to 40 °C | AF69: Bush or small tree | AG69: 2 years | AH69: 1000 to 1500 lemons per tree | AI69: #VALUE! | AJ69: 50gms | AR69: https://hasiruagro.com/wp-content/uploads/2023/08/finger-limeFruit-image-Hasiruagro.jpg
A70: HA0066 | B70: Grapes Mango | D70: Exotic fruits | E70: Fruiting Trees | F70: Exotic | G70: Yes | H70: No | I70: Grafted | O70: 820 | P70: 575 | Q70: 260 | T70: 83 | V70: Available | AA70: =IF(AND(N(Y70)>0,N(Z70)>0),ROUND(43560/(Y70*Z70),0),"") | AC70: Full sun | AE70: 20°C to 40 °C | AF70: Medium to big tree | AG70: 2 years | AH70: 80Kgs to 100Kgs per tree | AI70: March to June | AJ70: 100gms to 150gms
A71: HA0067 | B71: Guava L-49 | D71: Desi Fruits | E71: Fruiting Trees | F71: Desi | G71: Yes | H71: No | I71: Air layered | O71: 440 | P71: 310 | Q71: 120 | T71: 0 | V71: Out of Stock | Y71: 18 | Z71: 18 | AA71: =IF(AND(N(Y71)>0,N(Z71)>0),ROUND(43560/(Y71*Z71),0),"") | AB71: 18ft x 18ft | AC71: Full sun | AE71: 20°C to 40 °C | AF71: Medium sized tree | AG71: 2 years | AH71: 30Kg to 70kg | AI71: Round the year | AJ71: 150gms to 200gms | AR71: https://hasiruagro.com/wp-content/uploads/2023/08/Guava-L-49-Fruit-fruit-image-Hasiruagro.jpg
A72: HA0068 | B72: Guava Taiwan Seedless | D72: Desi Fruits | E72: Fruiting Trees | F72: Desi | G72: Yes | H72: No | I72: Air layered | O72: 350 | P72: 245 | Q72: 150 | T72: 0 | V72: Out of Stock | Y72: 18 | Z72: 18 | AA72: =IF(AND(N(Y72)>0,N(Z72)>0),ROUND(43560/(Y72*Z72),0),"") | AB72: 18ft x 18ft | AC72: Full sun | AE72: 20°C to 40 °C | AF72: Medium sized tree | AG72: 2 years | AH72: 30Kg to 70kg | AI72: Round the year | AJ72: 150gms to 200gms | AR72: https://hasiruagro.com/wp-content/uploads/2023/08/Guava-Taiwan-Seedless-fruit-image-Hasiruagro.jpg
A73: HA0070 | B73: Gumless Jackfruit | D73: Desi Fruits | E73: Fruiting Trees | F73: Desi | G73: Yes | H73: No | I73: Grafted | O73: 1325 | P73: 530 | Q73: 300 | T73: 0 | V73: Out of Stock | Y73: 20 | Z73: 20 | AA73: =IF(AND(N(Y73)>0,N(Z73)>0),ROUND(43560/(Y73*Z73),0),"") | AB73: 20ft x 20ft | AC73: Open sun | AE73: 20°C to 40 °C | AF73: Big tree | AG73: 2 years | AH73: 150 to 200 fruits | AI73: July to December | AJ73: Medium to Large | AR73: https://hasiruagro.com/wp-content/uploads/2023/07/Gumless-Jackfruit-F.webp
A74: HA0071 | B74: Hemachandra Jackfruit | D74: Desi Fruits | E74: Fruiting Trees | F74: Desi | G74: Yes | H74: No | I74: Grafted | O74: 1225 | P74: 490 | Q74: 260 | T74: 0 | V74: Out of Stock | Y74: 20 | Z74: 20 | AA74: =IF(AND(N(Y74)>0,N(Z74)>0),ROUND(43560/(Y74*Z74),0),"") | AB74: 20ft x 20ft | AC74: Open sun | AE74: 20°C to 40 °C | AF74: Big tree | AG74: 2 years | AH74: 150 to 200 fruits | AI74: July to December | AJ74: Medium to Large | AR74: https://hasiruagro.com/wp-content/uploads/2023/07/Hemachandra-Jackfruit-fruit-imag.webp
A75: HA0072 | B75: Hing | D75: Spices | E75: Other Plants | F75: Spices | G75: Yes | H75: No | I75: Seeded | O75: 1000 | P75: 700 | Q75: 400 | T75: 0 | V75: Out of Stock | AA75: =IF(AND(N(Y75)>0,N(Z75)>0),ROUND(43560/(Y75*Z75),0),"") | AB75: Medium tree | AC75: Partial shade | AE75: 20 – 30⁰C | AF75: Medium tree | AG75: 3 to 4 years | AH75: 100Kgs to 200Kgs per acre | AI75: Feb to April | AJ75: 5gms to 10gms | AR75: https://hasiruagro.com/wp-content/uploads/2023/08/Hing-fruit-image-Hasiruagro.jpg
A76: HA0073 | B76: Honge(Pongamia pinnata) | D76: Forestry | E76: Timber Trees | G76: Yes | H76: No | I76: Seeded | O76: 320 | P76: 225 | Q76: 60 | T76: 528 | V76: Available | Y76: 20 | Z76: 20 | AA76: =IF(AND(N(Y76)>0,N(Z76)>0),ROUND(43560/(Y76*Z76),0),"") | AB76: 20ft x 20ft | AC76: Full sun | AE76: 20°C to 40°C | AF76: 20ft to 30 ft tall | AG76: 5 to 6 years | AR76: https://hasiruagro.com/wp-content/uploads/2023/08/Honge-Pongamia-pinnata.jpg
A77: HA0074 | B77: Indian Olive (Amate) | D77: Exotic fruits | E77: Fruiting Trees | F77: Exotic | G77: Yes | H77: No | I77: Seeded | O77: 700 | P77: 490 | Q77: 250 | T77: 0 | V77: Out of Stock | AA77: =IF(AND(N(Y77)>0,N(Z77)>0),ROUND(43560/(Y77*Z77),0),"") | AC77: Full sun | AE77: 20°C to 40 °C | AF77: Medium tree | AG77: 5 years | AH77: 15Kgs to 20Kgs per tree | AI77: Septermber to January | AJ77: 70gms to 100gms | AR77: https://hasiruagro.com/wp-content/uploads/2024/03/Indian-Olive-Amate-fruit-hasiru-agro.webp
A78: HA0075 | B78: Jamun seedless | D78: Desi Fruits | E78: Fruiting Trees | F78: Desi | G78: Yes | H78: No | O78: 650 | P78: 455 | Q78: 180 | T78: 0 | V78: Out of Stock | Y78: 20 | Z78: 20 | AA78: =IF(AND(N(Y78)>0,N(Z78)>0),ROUND(43560/(Y78*Z78),0),"") | AB78: 20ft x 20ft | AC78: Open sun | AE78: 20°C to 40 °C | AF78: Big tree | AG78: 2 years | AH78: 60Kg to 70Kg | AI78: May to August | AJ78: 50gm to 100gm | AR78: https://hasiruagro.com/wp-content/uploads/2023/08/Jamun-seedless-fruit-image-Hasiruagro.jpg
A79: HA0076 | B79: Japanese Red diamond Guava | D79: Exotic fruits | E79: Fruiting Trees | F79: Exotic | G79: Yes | H79: No | I79: Air layered | O79: 800 | P79: 560 | Q79: 300 | T79: 0 | V79: Out of Stock | AA79: =IF(AND(N(Y79)>0,N(Z79)>0),ROUND(43560/(Y79*Z79),0),"") | AC79: Full sun/partial sun | AE79: 20°C to 40 °C | AF79: Small tree | AG79: 2 years | AH79: 30Kgs to 50Kgs | AI79: Alternate seasons | AJ79: 400gms to 1000gms | AR79: https://hasiruagro.com/wp-content/uploads/2023/08/Japanese-Red-diamond-GuavaFruit-image-Hasiruagro.jpg
A80: HA0077 | B80: Jardalu Mango | D80: Desi Fruits | E80: Fruiting Trees | F80: Desi | G80: Yes | H80: No | I80: Grafted | O80: 700 | P80: 490 | Q80: 250 | T80: 0 | V80: Out of Stock | Y80: 18 | Z80: 18 | AA80: =IF(AND(N(Y80)>0,N(Z80)>0),ROUND(43560/(Y80*Z80),0),"") | AB80: 18ft x 18ft | AC80: Open sun | AE80: 20°C to 40 °C | AF80: Medium sized tree | AG80: 2 years | AH80: 300 to 500 fruits | AI80: April to August | AJ80: 100gm to 150gm | AR80: https://hasiruagro.com/wp-content/uploads/2023/08/Jardalu-Mango-F.jpg
A81: HA0078 | B81: Jeerige Midi Mango | D81: Desi Fruits | E81: Fruiting Trees | F81: Desi | G81: Yes | H81: No | I81: Grafted | O81: 660 | P81: 460 | Q81: 250 | T81: 0 | V81: Out of Stock | Y81: 18 | Z81: 18 | AA81: =IF(AND(N(Y81)>0,N(Z81)>0),ROUND(43560/(Y81*Z81),0),"") | AB81: 18ft x 18ft | AC81: Open sun | AE81: 20°C to 40 °C | AF81: Medium sized tree | AG81: 2 years | AH81: 300 to 500 fruits | AI81: April to August | AJ81: 50gm to 100gm | AR81: https://hasiruagro.com/wp-content/uploads/2023/08/Jeerige-Midi-Mango-Fruit-image-Hasiruagro.jpg
A82: HA0079 | B82: Lemon Tree - All Season Kagzi lemon | D82: Desi Fruits | E82: Fruiting Trees | F82: Desi | G82: Yes | H82: No | I82: Grafted | O82: 440 | P82: 310 | Q82: 150 | T82: 1189 | V82: Available | Y82: 10 | Z82: 10 | AA82: =IF(AND(N(Y82)>0,N(Z82)>0),ROUND(43560/(Y82*Z82),0),"") | AB82: 10ft x 10ft | AC82: Open sun | AE82: 20°C to 40 °C | AF82: Small tree | AG82: 2 years | AH82: 80Kg to 100Kg | AI82: Year round | AJ82: 50gms to 80gms | AR82: https://hasiruagro.com/wp-content/uploads/2023/07/Lemon-Tree-All-Season-Kagzi-Hasiruagro.webp
A83: HA0080 | B83: Kaju badam | D83: Exotic fruits | E83: Fruiting Trees | F83: Exotic | G83: Yes | H83: No | I83: Seeded | O83: 520 | P83: 365 | Q83: 160 | T83: 0 | V83: Out of Stock | AA83: =IF(AND(N(Y83)>0,N(Z83)>0),ROUND(43560/(Y83*Z83),0),"") | AC83: Full sun | AE83: 20°C to 40 °C | AF83: Medium to big tree | AG83: 3 years | AH83: 8kgs to 10Kgs | AI83: January to July | AJ83: 50gms to 70gms | AR83: https://hasiruagro.com/wp-content/uploads/2023/08/Kaju-badam.jpg
A84: HA0081 | B84: Kesar Mango | D84: Desi Fruits | E84: Fruiting Trees | F84: Desi | G84: Yes | H84: No | I84: Grafted | O84: 700 | P84: 490 | Q84: 250 | T84: 37 | V84: Available | Y84: 18 | Z84: 18 | AA84: =IF(AND(N(Y84)>0,N(Z84)>0),ROUND(43560/(Y84*Z84),0),"") | AB84: 18ft x 18ft | AC84: Open sun | AE84: 20°C to 40 °C | AF84: Medium sized tree | AG84: 2 years | AH84: 300 to 500 fruits | AI84: April to August | AJ84: 200gm to 250gm | AR84: https://hasiruagro.com/wp-content/uploads/2023/07/Kesar-Mango-F.jpg
A85: HA0082 | B85: Kinnow Orange | D85: Desi Fruits | E85: Fruiting Trees | F85: Desi | G85: Yes | H85: No | O85: 500 | P85: 350 | Q85: 150 | T85: 39 | V85: Available | Y85: 18 | Z85: 18 | AA85: =IF(AND(N(Y85)>0,N(Z85)>0),ROUND(43560/(Y85*Z85),0),"") | AB85: 18ft x 18ft | AC85: Open sun | AE85: 15°C to 35 °C | AF85: Small tree | AG85: 2 years | AH85: 300 to 500 fruits | AI85: September to February | AJ85: 50gm to 100gm | AR85: https://hasiruagro.com/wp-content/uploads/2023/07/kinnow-orange.webp
A86: HA0083 | B86: Kiwi | D86: Exotic fruits | E86: Fruiting Trees | F86: Exotic | G86: Yes | H86: No | I86: Stem cuttings | O86: 700 | P86: 490 | Q86: 250 | T86: 0 | V86: Out of Stock | AA86: =IF(AND(N(Y86)>0,N(Z86)>0),ROUND(43560/(Y86*Z86),0),"") | AC86: Full sun | AE86: 16°C to 35 °C | AF86: Climber | AG86: 3 years | AH86: 30Kgs to 40Kgs | AI86: September to December | AJ86: 100gms to 150gms | AR86: https://hasiruagro.com/wp-content/uploads/2023/08/Kiwi.jpg
A87: HA0084 | B87: Kolkata Patti Lemon | D87: Desi Fruits | E87: Fruiting Trees | F87: Desi | G87: Yes | H87: No | I87: Grafted | O87: 560 | P87: 390 | Q87: 180 | T87: 0 | V87: Out of Stock | Y87: 10 | Z87: 10 | AA87: =IF(AND(N(Y87)>0,N(Z87)>0),ROUND(43560/(Y87*Z87),0),"") | AB87: 10ft x 10ft | AC87: Open sun | AE87: 20°C to 40 °C | AF87: small tree | AG87: 2 years | AH87: 80Kg to 100Kg | AI87: March to June | AJ87: 40g to 50g | AR87: https://hasiruagro.com/wp-content/uploads/2023/07/Kolkata-Patti-Lemon-fruit-image.webp
A88: HA0085 | B88: Loquat / Lakota | D88: Exotic fruits | E88: Fruiting Trees | F88: Exotic | G88: Yes | H88: No | I88: Grafted | O88: 1100 | P88: 770 | Q88: 150 | T88: 0 | V88: Out of Stock | AA88: =IF(AND(N(Y88)>0,N(Z88)>0),ROUND(43560/(Y88*Z88),0),"") | AC88: Full shade | AE88: 16°C to 35 °C | AF88: Big tree | AG88: 4 years | AH88: 15Kgs to 20Kgs per tree | AI88: Septermber to January | AJ88: 70gms to 100gms | AR88: https://hasiruagro.com/wp-content/uploads/2023/07/Loquat-F.jpg
A89: HA0086 | B89: Lakshmanphal | D89: Desi Fruits | E89: Fruiting Trees | F89: Desi | G89: Yes | H89: No | I89: Grafted | O89: 560 | P89: 390 | Q89: 180 | T89: 20 | V89: Available | Y89: 18 | Z89: 18 | AA89: =IF(AND(N(Y89)>0,N(Z89)>0),ROUND(43560/(Y89*Z89),0),"") | AB89: 18ft x 18ft | AC89: Open sun | AE89: 20°C to 40 °C | AF89: Medium sized tree | AG89: 2 years | AH89: 20 to 30 fruits | AI89: April to August | AJ89: 1Kg to 1.5Kg | AR89: https://hasiruagro.com/wp-content/uploads/2023/08/Lakshmanphal-fruit-image-Hasiruagro.jpg
A90: HA0087 | B90: Lalbhag Madhura Jackfruit | D90: Desi Fruits | E90: Fruiting Trees | F90: Desi | G90: Yes | H90: No | I90: Grafted | O90: 1225 | P90: 490 | Q90: 260 | T90: 0 | V90: Out of Stock | Y90: 20 | Z90: 20 | AA90: =IF(AND(N(Y90)>0,N(Z90)>0),ROUND(43560/(Y90*Z90),0),"") | AB90: 20ft x 20ft | AC90: Open sun | AE90: 20°C to 40 °C | AF90: Big tree | AG90: 2 years | AH90: 250 to 300 fruits | AI90: July to December | AJ90: Medium to Large | AR90: https://hasiruagro.com/wp-content/uploads/2023/07/Lalbhag-Madhura-Jackfruit-F.webp
A91: HA0088 | B91: Lilli Pilli | D91: Exotic fruits | E91: Fruiting Trees | F91: Exotic | G91: Yes | H91: No | I91: Seeded | O91: 1100 | P91: 770 | Q91: 450 | T91: 0 | V91: Out of Stock | AA91: =IF(AND(N(Y91)>0,N(Z91)>0),ROUND(43560/(Y91*Z91),0),"") | AC91: Full sun | AE91: 20°C to 40 °C | AF91: Small to Medium tree | AG91: 4 years | AH91: 100Kgs to 200Kgs per year | AI91: Round the yesr | AJ91: 50gms to 70gms | AR91: https://hasiruagro.com/wp-content/uploads/2023/08/Lilli-Pilli-Fruit-image-Hasiruagro.jpg
A92: HA0089 | B92: Litchi seedless | D92: Desi Fruits | E92: Fruiting Trees | F92: Desi | G92: Yes | H92: No | I92: Grafted | O92: 680 | P92: 475 | Q92: 200 | T92: 0 | V92: Out of Stock | Y92: 25 | Z92: 25 | AA92: =IF(AND(N(Y92)>0,N(Z92)>0),ROUND(43560/(Y92*Z92),0),"") | AB92: 25ft x 25ft | AC92: Full sun | AE92: 15°C to 38°C | AF92: Medium sized tree | AG92: 3 years | AH92: 80Kg to 150Kg | AI92: April to July | AJ92: 50gms to 70gms | AR92: https://hasiruagro.com/wp-content/uploads/2023/08/Litchi-Seedless-F.jpg
A93: HA0090 | B93: Longon | D93: Exotic fruits | E93: Fruiting Trees | F93: Exotic | G93: Yes | H93: No | I93: Seeded | O93: 2800 | P93: 1960 | Q93: 1300 | T93: 0 | V93: Out of Stock | AA93: =IF(AND(N(Y93)>0,N(Z93)>0),ROUND(43560/(Y93*Z93),0),"") | AC93: Full sun | AE93: 20°C to 35°C | AF93: Small to medium sized tree | AG93: 3 years | AH93: 150Kgs to 200Kgs per tree | AI93: January to August | AJ93: 3gm to 800gm | AR93: https://hasiruagro.com/wp-content/uploads/2023/08/Longan-F.jpg
A94: HA0091 | B94: Australian Macadamia Nut plant | D94: Exotic fruits | E94: Fruiting Trees | F94: Exotic | G94: Yes | H94: No | I94: Seeded | O94: 1925 | P94: 770 | Q94: 400 | T94: 3807 | V94: Available | Y94: 18 | Z94: 18 | AA94: =IF(AND(N(Y94)>0,N(Z94)>0),ROUND(43560/(Y94*Z94),0),"") | AB94: 18ft x 18ft | AC94: Full sun | AE94: 20°C to 45°C | AF94: Medium to large tree (50ft to 80ft tall) | AG94: 5 years | AH94: 35Kg to 50Kg | AI94: March to September | AJ94: 15gm to 25gm | AR94: https://hasiruagro.com/wp-content/uploads/2023/07/Australian-Macadamia-Nuts-plant-Hasiruagro.webp
A95: HA0092 | B95: Mahagony | D95: Forestry | E95: Timber Trees | G95: Yes | H95: No | I95: Seeded | O95: 360 | P95: 250 | Q95: 60 | T95: 12 | V95: Available | Y95: 25 | Z95: 25 | AA95: =IF(AND(N(Y95)>0,N(Z95)>0),ROUND(43560/(Y95*Z95),0),"") | AB95: 25ft x 25ft | AC95: Full sun | AE95: 20°C to 40°C | AF95: 30ft to 60ft tall | AG95: 10 years | AH95: 30 to 50 cft of lumber | AR95: https://hasiruagro.com/wp-content/uploads/2023/08/mahogany.jpg
A96: HA0094 | B96: Malaysian dwarf Jackfruit | D96: Desi Fruits | E96: Fruiting Trees | F96: Desi | G96: Yes | H96: No | I96: Grafted | O96: 1262 | P96: 505 | Q96: 260 | T96: 0 | V96: Out of Stock | Y96: 20 | Z96: 20 | AA96: =IF(AND(N(Y96)>0,N(Z96)>0),ROUND(43560/(Y96*Z96),0),"") | AB96: 20ft x 20ft | AC96: Open sun | AE96: 20°C to 40 °C | AF96: Medium sized tree | AG96: 2 years | AH96: 150 to 200 fruits | AI96: July to December | AJ96: 3-4 kg per fruit | AR96: https://hasiruagro.com/wp-content/uploads/2023/07/Malaysian-dwarf-Jackfruit-fruit.webp
A97: HA0095 | B97: Mallika Mango | D97: Desi Fruits | E97: Fruiting Trees | F97: Desi | G97: Yes | H97: No | I97: Grafted | O97: 700 | P97: 490 | Q97: 250 | T97: 286 | V97: Available | Y97: 18 | Z97: 18 | AA97: =IF(AND(N(Y97)>0,N(Z97)>0),ROUND(43560/(Y97*Z97),0),"") | AB97: 18ft x 18ft | AC97: Open sun | AE97: 20°C to 40 °C | AF97: Medium sized tree | AG97: 2 years | AH97: 300 to 500 fruits | AI97: April to August | AJ97: 100gm to 150gm | AR97: https://hasiruagro.com/wp-content/uploads/2023/08/Mallika-Mango-F.jpg
A98: HA0096 | B98: Mandarin Orange | D98: Exotic fruits | E98: Fruiting Trees | F98: Exotic | G98: Yes | H98: No | I98: Grafted | O98: 560 | P98: 390 | Q98: 180 | T98: 18 | V98: Available | AA98: =IF(AND(N(Y98)>0,N(Z98)>0),ROUND(43560/(Y98*Z98),0),"") | AC98: Full sun | AE98: 20°C to 40 °C | AF98: Medium tree | AG98: 2 years | AH98: 250 to 350 oranges per tree | AI98: Year round | AJ98: 80gms to 150gms | AR98: https://hasiruagro.com/wp-content/uploads/2023/07/Mandrin-Orange.webp
A99: HA0097 | B99: Mangosteen (1.5ft) | D99: Exotic fruits | E99: Fruiting Trees | F99: Exotic | G99: Yes | H99: No | I99: Seeded | O99: 900 | P99: 630 | Q99: 350 | T99: 162 | V99: Available | AA99: =IF(AND(N(Y99)>0,N(Z99)>0),ROUND(43560/(Y99*Z99),0),"") | AC99: Full shade | AE99: 16°C to 35 °C | AF99: Medium tree | AG99: 5 years | AH99: 100Kgs to 200Kgs per tree | AI99: May to August | AJ99: 150gms to 200gms | AR99: https://hasiruagro.com/wp-content/uploads/2023/08/Mangosteen-F.jpg
A100: HA0098 | B100: Mangosteen (6ft) | D100: Exotic fruits | E100: Fruiting Trees | F100: Exotic | G100: Yes | H100: No | I100: Seeded | O100: 2180 | P100: 1525 | Q100: 990 | T100: 0 | V100: Out of Stock | AA100: =IF(AND(N(Y100)>0,N(Z100)>0),ROUND(43560/(Y100*Z100),0),"") | AC100: Full shade | AE100: 16°C to 35 °C | AF100: Medium tree | AG100: 3 years | AH100: 100Kgs to 200Kgs per tree | AI100: May to August | AJ100: 150gms to 200gms | AR100: https://hasiruagro.com/wp-content/uploads/2023/08/Mangosteen-F.jpg
A101: HA0099 | B101: Mankale red Jackfruit | D101: Desi Fruits | E101: Fruiting Trees | F101: Desi | G101: Yes | H101: No | I101: Grafted | O101: 1225 | P101: 490 | Q101: 280 | T101: 0 | V101: Out of Stock | Y101: 20 | Z101: 20 | AA101: =IF(AND(N(Y101)>0,N(Z101)>0),ROUND(43560/(Y101*Z101),0),"") | AB101: 20ft x 20ft | AC101: Open sun | AE101: 20°C to 40 °C | AF101: Big tree | AG101: 2 years | AH101: 150 to 200 fruits | AI101: July to December | AJ101: Medium to Large | AR101: https://hasiruagro.com/wp-content/uploads/2023/07/Mankale-red-Jackfruit-fruit-imag.webp
...

Sheet Input Products
A1: Input Products
A2: Compost, vermicompost, biochar, seeds, liquid fertiliser, bio-pesticide. One row per pack size.
A4: SKU | B4: Product Name | C4: Kannada Name | D4: Category | E4: Pack Size | F4: Unit (kg / L / g / packet) | G4: Pack Weight (kg) | H4: Regular Price (Rs) | I4: Offer Price (Rs) | J4: Current Stock | K4: Low Stock Alert at | L4: Availability | M4: HSN Code | N4: GST % | O4: Short Description | P4: How to Use / Dosage | Q4: Recommended with which plants / models | R4: Best Seller? | S4: Image available? | T4: Notes
D5: Compost
D6: Vermicompost
D7: Biochar
D8: Seeds
D9: Liquid Fertiliser
D10: Bio-Pesticide

Sheet Recommendation Models
A1: Recommendation Models (Help Me Choose)
A2: For each model, list the plants and their role. The site scales the 36 x 36 ft block to the customer's land size.
A4: Model | B4: Short description for customers | C4: Plant density (plants per 36 x 36 ft) | D4: Plants per acre | E4: Row pattern in 36 x 36 ft (e.g. M o X o X o M) | F4: Legend (what M / o / X mean) | G4: Min land size | H4: Planting video URL | I4: Notes
A5: Commercial
A6: Food Forest
A7: Miyawaki
A11: Plants in each model
A12: Model | B12: Plant Name (as in Plants tab) | C12: Category | D12: Role (Main / Host / Biomass) | E12: Layer | F12: Spacing L (ft) | G12: Spacing W (ft) | H12: Qty per 36 x 36 ft | I12: Qty per acre (auto) | J12: Swap options (alternative plants) | K12: Vermicompost per plant (kg) | L12: Biochar per plant (kg) | M12: Notes
A13: Commercial | I13: =IF(N(H13)>0,ROUND(H13*43560/1296,0),"")
A14: Food Forest | I14: =IF(N(H14)>0,ROUND(H14*43560/1296,0),"")
A15: Miyawaki | I15: =IF(N(H15)>0,ROUND(H15*43560/1296,0),"")
I16: =IF(N(H16)>0,ROUND(H16*43560/1296,0),"")
I17: =IF(N(H17)>0,ROUND(H17*43560/1296,0),"")
I18: =IF(N(H18)>0,ROUND(H18*43560/1296,0),"")
I19: =IF(N(H19)>0,ROUND(H19*43560/1296,0),"")
I20: =IF(N(H20)>0,ROUND(H20*43560/1296,0),"")
I21: =IF(N(H21)>0,ROUND(H21*43560/1296,0),"")
I22: =IF(N(H22)>0,ROUND(H22*43560/1296,0),"")
I23: =IF(N(H23)>0,ROUND(H23*43560/1296,0),"")
I24: =IF(N(H24)>0,ROUND(H24*43560/1296,0),"")
I25: =IF(N(H25)>0,ROUND(H25*43560/1296,0),"")
I26: =IF(N(H26)>0,ROUND(H26*43560/1296,0),"")
I27: =IF(N(H27)>0,ROUND(H27*43560/1296,0),"")
... I72: =IF(N(H72)>0,ROUND(H72*43560/1296,0),"")

Sheet Calculators
A1: Calculator Formulas
A2: Our proposed formula is shown. Please confirm or replace it in the yellow column.
A4: Calculator | B4: Where used | C4: Proposed formula (WODO) | D4: Inputs the customer enters | E4: Hasiru Agro formula / correction | F4: Example to test | G4: Approved?
A5: Plants per acre | B5: Home, Shop (floating) | C5: Plants per acre = 43,560 / (spacing L ft x spacing W ft). Optional: + buffer % for replacements. | D5: Spacing L and W (ft), or plant picked (auto-fills its spacing), land size | F5: 10 x 10 ft -> 436 plants/acre
A6: Buffer / mortality allowance | B6: Plant calculator | C6: Add X% extra plants for replacements (sketch shows '43,560 x 3 / 100'; is that a 3% allowance?). | D6: -
A7: Compost requirement | B7: Home compost calculator | C7: Compost kg = sum over plants (qty x compost kg per plant). | D7: Plants and quantities selected | F7: 500 plants -> ? kg
A8: Vermicompost requirement | B8: Recommendation page, Cart | C8: Vermicompost kg = sum (qty x kg per plant, by plant size/type). | D8: Plants selected | F8: 500 plants -> ? kg
A9: Biochar requirement | B9: Recommendation page, Cart | C9: Biochar kg = sum (qty x kg per plant). | D9: Plants selected | F9: 500 plants -> ? kg
A10: Seed requirement | B10: Recommendation page | C10: Seeds (g or packets) per acre or per 36 x 36 block, e.g. for ground cover / green manure. | D10: Land size, model
A11: Model scaling | B11: Help Me Choose | C11: Plants for land = qty per 36 x 36 ft block x (land sq ft / 1,296). | D11: Land size (acre or sq ft) | F11: 1 acre = 33.6 blocks
A12: Pack rounding | B12: Cart | C12: Input kg rounded up to whole packs (e.g. 112 kg -> 5 x 25 kg). | D12: -

Sheet Logistics
A1: Delivery, Truck Capacity and Packing
A2: Needed for the truck-capacity meter, delivery charges and packing charges.
A4: A. Vehicles
A5: Vehicle type | B5: Max weight (kg) | C5: Max plants (small saplings) | D5: Max plants (large / 6 ft+) | E5: Rate per km (Rs) | F5: Minimum charge (Rs) | G5: Notes
A6: Tata Ace / small pickup
A7: Bolero pickup
A8: 407 / mid truck
A9: Large truck
A13: B. Bengaluru scheduled delivery
A14: Setting | B14: Value | G14: Notes
A15: Delivery day(s) of week
A16: Order cut-off (day + time)
A17: Delivery charge (flat / slab)
A18: Free delivery above (Rs)
A19: PIN codes / areas covered
A20: Max distance from nursery (km)
A23: C. Outstation delivery
A24: Rule | B24: Value | G24: Notes
A25: Rate per km (Rs)
A26: Rate per kg (Rs)
A27: Minimum order for outstation (Rs / plants)
A28: States / districts served
A29: Delivery lead time (days)
A30: Shared truck / part-load allowed?
A31: Who pays tolls / loading?
A34: D. Packing charges
A35: Rule | B35: Value | G35: Notes
A36: Packing type (per order / per plant / per kg / by size)
A37: Rate
A38: Free packing above (Rs)
A39: Special packing for large plants
A40: Courier option for single plants?
A43: E. Nursery pickup
A44: Setting | B44: Value | G44: Notes
A45: Nursery address + Google Maps link
A46: Pickup days and timings
A47: Ready-for-pickup time after order
A48: Contact number for pickup

Sheet Content & Policies
A1: Content, Media and Policies Checklist
A2: Share files in a shared Google Drive folder and mark the status here.
A4: Item | B4: Used on | C4: Details needed | D4: Status | E4: Drive link / Notes
A5: Home banner image + headline | B5: Home | C5: 1-3 hero images (farm / nursery), headline idea. | D5: Pending
A6: Logos: UAS Dharwad, Startup India, MSME, others | B6: Home band, About | C6: High-res logos and approved wording ('Incubated by UAS Dharwad, recognised by Startup India'). | D6: Pending
A7: Proven results numbers | B7: Why Choose Us, Farm Dev | C7: Total acres developed, farms developed, clients, projects, plants planted (verified). Current site says 120+ farms, 850+ acres; please confirm. | D7: Pending
A8: Why Choose Us points | B8: Home, Why Choose Us | C8: Plant authenticity (how quality is ensured), domain expertise, delivery to farm. | D8: Pending
A9: About Us | B9: About | C9: Chemical-free approach, certified permaculture designer (certificate copy), vision, mission, team photos. | D9: Pending
A10: Testimonials | B10: Home | C10: Name, location, photo, review, rating (1-5), farm/project details. Minimum 6. | D10: Pending
A11: DIY / Learn-how videos | B11: Home, Recommendation | C11: YouTube links, title, category, which model it belongs to (Commercial / Food Forest / Miyawaki). | D11: Pending
A12: Our Work (projects) | B12: Farm Development | C12: Per project: photos, before/after, location, acres, scope of work. | D12: Pending
A13: Our Clients | B13: Farm Development | C13: Client name (permission to show), project type, location, acreage, work done. | D13: Pending
A14: Damage policy | B14: Checkout, footer, policy page | C14: Reporting window (e.g. 48 hours), photo/video proof, what is covered. | D14: Pending
A15: Replacement policy | B15: Checkout, footer, policy page | C15: When a replacement is given, timeline, delivery of replacement. | D15: Pending
A16: Cancellation / return policy | B16: Checkout, footer, policy page | C16: Confirmed: no cancellation or return. Any exception (e.g. order not dispatched)? | D16: Pending
... A25: Product photos | B25: Shop | C25: New photos for plants marked 'New Photo Needed?' = Yes, and all input products. | D25: Pending

Sheet Category Map
A1: Category Mapping (proposed)
A2: Old shop had 5 categories. The SRS asks for Timber / Fruiting / Other. Please approve or change.
A4: Old category | B4: No. of plants | C4: Proposed new category | D4: Proposed filter / sub-category | E4: Approved? / Change to
A5: Forestry | B5: =COUNTIF(Plants!D:D,A5) | C5: Timber Trees | D5: -
A6: Desi Fruits | B6: =COUNTIF(Plants!D:D,A6) | C6: Fruiting Trees | D6: Desi
A7: Exotic fruits | B7: =COUNTIF(Plants!D:D,A7) | C7: Fruiting Trees | D7: Exotic
A8: Spices | B8: =COUNTIF(Plants!D:D,A8) | C8: Other Plants | D8: Spices
A9: Plantation | B9: =COUNTIF(Plants!D:D,A9) | C9: Other Plants | D9: Plantation
A11: Input categories (new): Compost, Vermicompost, Biochar, Seeds, Liquid Fertiliser, Bio-Pesticide. Add more if needed.
